observableprops/__init__.py
observableprops-0.2.0.dist-info/LICENSE
observableprops-0.2.0.dist-info/METADATA
observableprops-0.2.0.dist-info/WHEEL
observableprops-0.2.0.dist-info/top_level.txt
observableprops-0.2.0.dist-info/RECORD
